MANIFEST.in
setup.py
tests_web_linda/__init__.py
tests_web_linda/main.py
tests_web_linda/version.py
tests_web_linda.egg-info/PKG-INFO
tests_web_linda.egg-info/SOURCES.txt
tests_web_linda.egg-info/dependency_links.txt
tests_web_linda.egg-info/entry_points.txt
tests_web_linda.egg-info/requires.txt
tests_web_linda.egg-info/top_level.txt
tests_web_linda/app/README.md
tests_web_linda/app/behave.ini
tests_web_linda/app/browser.properties
tests_web_linda/app/environment.properties
tests_web_linda/app/package-lock.json
tests_web_linda/app/package.json
tests_web_linda/app/src/test/cucumber.json
tests_web_linda/app/src/test/config/delete_folders.py
tests_web_linda/app/src/test/features/1_registro.feature
tests_web_linda/app/src/test/features/2_login.feature
tests_web_linda/app/src/test/library/generate_word.py
tests_web_linda/app/src/test/library/generate_word_v2.py
tests_web_linda/app/src/test/library/util_web.py
tests_web_linda/app/src/test/library/__pycache__/util_web.cpython-310.pyc
tests_web_linda/app/src/test/pages/pages_OpenCart.py
tests_web_linda/app/src/test/pages/pages_appTsoft.py
tests_web_linda/app/src/test/pages/pages_appURPI.py
tests_web_linda/app/src/test/pages/pages_reporteUFT.py
tests_web_linda/app/src/test/pages/__pycache__/pages_OpenCart.cpython-310.pyc
tests_web_linda/app/src/test/pages/__pycache__/pages_reporteUFT.cpython-310.pyc
tests_web_linda/app/src/test/resources/data/json/credentials.json
tests_web_linda/app/src/test/resources/drivers/chromedriver.exe
tests_web_linda/app/src/test/resources/drivers/geckodriver.exe
tests_web_linda/app/src/test/resources/drivers/msedgedriver.exe
tests_web_linda/app/src/test/resources/drivers/linux/chromedriver
tests_web_linda/app/src/test/resources/drivers/windows/chromedriver.exe
tests_web_linda/app/src/test/resources/drivers/windows/geckodriver.exe
tests_web_linda/app/src/test/resources/drivers/windows/msedgedriver.exe
tests_web_linda/app/src/test/resources/reports/cucumber-html-reports/overview-failures.html
tests_web_linda/app/src/test/resources/reports/cucumber-html-reports/overview-features.html
tests_web_linda/app/src/test/resources/reports/cucumber-html-reports/overview-steps.html
