Metadata-Version: 2.1
Name: tests-web-linda
Version: 2.0
Summary: A simple functional test library using Selenium and Chrome driver
Home-page: UNKNOWN
Author: Linda Lopez
License: UNKNOWN
Platform: UNKNOWN
Classifier: Development Status :: 3 - Alpha
Classifier: Intended Audience :: Developers
Classifier: License :: OSI Approved :: MIT License
Classifier: Programming Language :: Python
